okland/__init__.py
okland/__main__.py
okland/generics.py
okland/kics.py
okland-0.0.7.dist-info/LICENSE.txt
okland-0.0.7.dist-info/METADATA
okland-0.0.7.dist-info/WHEEL
okland-0.0.7.dist-info/entry_points.txt
okland-0.0.7.dist-info/top_level.txt
okland-0.0.7.dist-info/RECORD
