Metadata-Version: 2.1
Name: okland
Version: 0.0.7
Summary: Prometheus metrics from static code analysis toolings.
Home-page: https://github.com/la3mmchen/okland/
Author: la3mmchen
Author-email: alex@k3wl.net
License: MIT
Project-URL: Documentation, https://github.com/la3mmchen/okland/readme.md
Platform: any
Classifier: Development Status :: 4 - Beta
Classifier: Programming Language :: Python
License-File: LICENSE.txt
Requires-Dist: fire (==0.4.0)
Requires-Dist: PyYAML (==6.0)
Requires-Dist: pytest (==7.1.3)
Requires-Dist: pytest-xdist (==2.5.0)
Requires-Dist: coverage (==6.5.0)
Requires-Dist: flake8 (==5.0.4)
Requires-Dist: rich (==12.5.1)
Requires-Dist: prometheus-client (==0.14.1)
Requires-Dist: docker (==5.0.3)
Requires-Dist: tox (==3.26.0)
Requires-Dist: twine (==4.0.1)
Provides-Extra: testing
Requires-Dist: setuptools ; extra == 'testing'
Requires-Dist: pytest ; extra == 'testing'
Requires-Dist: pytest-cov ; extra == 'testing'
